wiki_fmt/__init__.py
wiki_fmt/cli.py
wiki_fmt/formatter.py
wiki_fmt-1.0.0.dist-info/licenses/LICENSE
wiki_fmt-1.0.0.dist-info/METADATA
wiki_fmt-1.0.0.dist-info/WHEEL
wiki_fmt-1.0.0.dist-info/entry_points.txt
wiki_fmt-1.0.0.dist-info/top_level.txt
wiki_fmt-1.0.0.dist-info/RECORD
