Metadata-Version: 2.4
Name: wiki-fmt
Version: 1.0.0
Summary: 一个 Confluence 文档自动排版工具，支持 LLM 智能排版优化
Home-page: https://github.com/water/wiki-fmt
Author: water
Author-email: water <yywater68@gmail.com>
License: MIT
Project-URL: Homepage, https://github.com/water/wiki-fmt
Project-URL: Issues, https://github.com/water/wiki-fmt/issues
Project-URL: Repository, https://github.com/water/wiki-fmt.git
Classifier: Development Status :: 4 - Beta
Classifier: Intended Audience :: Developers
Classifier: License :: OSI Approved :: MIT License
Classifier: Operating System :: OS Independent
Classifier: Programming Language :: Python :: 3
Classifier: Programming Language :: Python :: 3.8
Classifier: Programming Language :: Python :: 3.9
Classifier: Programming Language :: Python :: 3.10
Classifier: Programming Language :: Python :: 3.11
Classifier: Programming Language :: Python :: 3.12
Requires-Python: >=3.8
License-File: LICENSE
Requires-Dist: requests>=2.28.0
Requires-Dist: python-dotenv>=0.19.0
Requires-Dist: beautifulsoup4>=4.11.0
Requires-Dist: openai>=1.0.0
Requires-Dist: atlassian-python-api>=3.41.0
Requires-Dist: lxml>=4.9.0
Requires-Dist: markdown>=3.4.0
Dynamic: author
Dynamic: home-page
Dynamic: license-file
Dynamic: requires-python
